requisitions/__init__.py
requisitions/ncbi.py
requisitions/py.typed
requisitions-0.1.0.dev0.dist-info/WHEEL
requisitions-0.1.0.dev0.dist-info/METADATA
requisitions-0.1.0.dev0.dist-info/RECORD
