Metadata-Version: 2.3
Name: requisitions
Version: 0.1.0.dev0
Summary: Add your description here
Author: Caleb R.
Author-email: Caleb R. <hyletic@proton.me>
Requires-Dist: python-dotenv>=1.2.1
Requires-Dist: requests>=2.32.5
Requires-Python: >=3.10
